[
    {
        "blogId": 0,
        "title" : "Featured Post",
        "largetitle" : "Step-by-step guide to choosing great font pairs",
        "by" : "John Doe", 
        "date" : "May 23 2022",
        "desc" : "Duis aute irure dolor in reprehenderit in voluptate velit esse cillum dolore eu fugiat nulla pariatur. Excepteur sint occaecat cupidatat non proident.",
        "type" : "Bible",
        "image": "../assets/images/biblia.jpg"      
       
    },
    {
        "blogId": 1,
        "title" : "Featured Post",
        "largetitle" : "Step-by-step guide to choosing great font pairs",
        "by" : "John Doe", 
        "date" : "May 23 2022",
        "desc" : "Duis aute irure dolor in reprehenderit in voluptate velit esse cillum dolore eu fugiat nulla pariatur. Excepteur sint occaecat cupidatat non proident.",
        "image": "../assets/images/igreja.jpg",
        "type" : "Church" 
    },
    {
        "blogId": 2,
        "title" : "Featured Post",
        "largetitle" : "Step-by-step guide to choosing great font pairs",
        "by" : "John Doe", 
        "date" : "May 23 2022",
        "desc" : "Duis aute irure dolor in reprehenderit in voluptate velit esse cillum dolore eu fugiat nulla pariatur. Excepteur sint occaecat cupidatat non proident.",
        "image": "../assets/images/rosario.jpg",
        "type" : "Rosary" 
    },
    {
        "blogId": 3,
        "title" : "Featured Post",
        "largetitle" : "Step-by-step guide to choosing great font pairs",
        "by" : "John Doe", 
        "date" : "May 23 2022",
        "desc" : "Duis aute irure dolor in reprehenderit in voluptate velit esse cillum dolore eu fugiat nulla pariatur. Excepteur sint occaecat cupidatat non proident.",
        "image": "../assets/images/tecnoliga.jpg",
        "type" : "Technology" 
    },
    {
        "blogId": 4,
        "title" : "Featured Post",
        "largetitle" : "Step-by-step guide to choosing great font pairs",
        "by" : "John Doe", 
        "date" : "May 23 2022",
        "desc" : "Duis aute irure dolor in reprehenderit in voluptate velit esse cillum dolore eu fugiat nulla pariatur. Excepteur sint occaecat cupidatat non proident.",
        "image": "../assets/images/viagens.jpg",
        "type" : "Vocation" 
    },
    {
        "blogId": 5,
        "title" : "Featured Post",
        "largetitle" : "Step-by-step guide to choosing great font pairs",
        "by" : "John Doe", 
        "date" : "May 23 2022",
        "desc" : "Duis aute irure dolor in reprehenderit in voluptate velit esse cillum dolore eu fugiat nulla pariatur. Excepteur sint occaecat cupidatat non proident.",
        "image": "../assets/images/cafe.jpg",
        "type" : "Lazer" 
    },
    {
        "blogId": 6,
        "title" : "Featured Post",
        "largetitle" : "How to build rapport with your web design clients",
        "by" : "John Doe", 
        "date" : "May 23 2022",
        "desc" : "Duis aute irure dolor in reprehenderit in voluptate velit esse cillum dolore eu fugiat nulla pariatur. Excepteur sint occaecat cupidatat non proident.",
        "image": "../assets/images/negocio.jpg",
        "type" : "Business" 
    },
    {
        "blogId": 7,
        "title" : "Featured Post",
        "largetitle" : "Step-by-step guide to choosing great font pairs",
        "by" : "John Doe", 
        "date" : "May 23 2022",
        "desc" : "Duis aute irure dolor in reprehenderit in voluptate velit esse cillum dolore eu fugiat nulla pariatur. Excepteur sint occaecat cupidatat non proident.",
        "image": "../assets/images/reuniao.jpg",
        "type" : "Economy" 
    },

    {
        "blogId": 8,
        "title" : "Featured Post",
        "largetitle" : "Design tips for designers that cover everything you need",
        "by" : "John Doe", 
        "date" : "May 23 2022",
        "desc" : "Duis aute irure dolor in reprehenderit in voluptate velit esse cillum dolore eu fugiat nulla pariatur. Excepteur sint occaecat cupidatat non proident.",
        "image": "../assets/images/fazendo.jpg",
        "type" : "Startup" 
    },

    {
        "blogId": 9,
        "title" : "Featured Post",
        "largetitle" : "Design tips for designers that cover everything you need",
        "by" : "John Doe", 
        "date" : "May 23 2022",
        "desc" : "Duis aute irure dolor in reprehenderit in voluptate velit esse cillum dolore eu fugiat nulla pariatur. Excepteur sint occaecat cupidatat non proident.",
        "image": "../assets/images/carro.jpg",
        "type" : "Car" 
    },

    {
        "blogId": 10,
        "title" : "Featured Post",
        "largetitle" : "Design tips for designers that cover everything you need",
        "by" : "John Doe", 
        "date" : "May 23 2022",
        "desc" : "Duis aute irure dolor in reprehenderit in voluptate velit esse cillum dolore eu fugiat nulla pariatur. Excepteur sint occaecat cupidatat non proident.",
        "image": "../assets/images/cultura.jpg",
        "type" : "Cultura" 
    },

    {
        "blogId": 11,
        "title" : "Featured Post",
        "largetitle" : "Design tips for designers that cover everything you need",
        "by" : "John Doe", 
        "date" : "May 23 2022",
        "desc" : "Duis aute irure dolor in reprehenderit in voluptate velit esse cillum dolore eu fugiat nulla pariatur. Excepteur sint occaecat cupidatat non proident.",
        "image": "../assets/images/transporte.jpg",
        "type" : "transporte" 
    },

    {
        "blogId": 12,
        "title" : "Featured Post",
        "largetitle" : "Design tips for designers that cover everything you need",
        "by" : "John Doe", 
        "date" : "May 23 2022",
        "desc" : "Duis aute irure dolor in reprehenderit in voluptate velit esse cillum dolore eu fugiat nulla pariatur. Excepteur sint occaecat cupidatat non proident.",
        "image": "../assets/images/desporto.jpg",
        "type" : "Desporto" 
    },

    {
        "blogId": 13,
        "title" : "Featured Post",
        "largetitle" : "Design tips for designers that cover everything you need",
        "by" : "John Doe", 
        "date" : "May 23 2022",
        "desc" : "Duis aute irure dolor in reprehenderit in voluptate velit esse cillum dolore eu fugiat nulla pariatur. Excepteur sint occaecat cupidatat non proident.",
        "image": "../assets/images/leitura.jpg",
        "type" : "Leitura" 
    },

    {
        "blogId": 14,
        "title" : "Featured Post",
        "largetitle" : "Design tips for designers that cover everything you need",
        "by" : "John Doe", 
        "date" : "May 23 2022",
        "desc" : "Duis aute irure dolor in reprehenderit in voluptate velit esse cillum dolore eu fugiat nulla pariatur. Excepteur sint occaecat cupidatat non proident.",
        "image": "../assets/images/cidade.jpg",
        "type" : "City" 
    },

    {
        "blogId": 15,
        "title" : "Featured Post",
        "largetitle" : "Design tips for designers that cover everything you need",
        "by" : "John Doe", 
        "date" : "May 23 2022",
        "desc" : "Duis aute irure dolor in reprehenderit in voluptate velit esse cillum dolore eu fugiat nulla pariatur. Excepteur sint occaecat cupidatat non proident.",
        "image": "../assets/images/mulher.jpg",
        "type" : "Mulher" 
    },

    {
        "blogId": 16,
        "title" : "Featured Post",
        "largetitle" : "Design tips for designers that cover everything you need",
        "by" : "John Doe", 
        "date" : "May 23 2022",
        "desc" : "Duis aute irure dolor in reprehenderit in voluptate velit esse cillum dolore eu fugiat nulla pariatur. Excepteur sint occaecat cupidatat non proident.",
        "image": "../assets/images/vestuario.jpg",
        "type" : "Vestuário" 
    },

    {
        "blogId": 17,
        "title" : "Featured Post",
        "largetitle" : "Design tips for designers that cover everything you need",
        "by" : "John Doe", 
        "date" : "May 23 2022",
        "desc" : "Duis aute irure dolor in reprehenderit in voluptate velit esse cillum dolore eu fugiat nulla pariatur. Excepteur sint occaecat cupidatat non proident.",
        "image": "../assets/images/montanha.jpg",
        "type" : "Montanha" 
    },

    {
        "blogId": 18,
        "title" : "Featured Post",
        "largetitle" : "Design tips for designers that cover everything you need",
        "by" : "John Doe", 
        "date" : "May 23 2022",
        "desc" : "Duis aute irure dolor in reprehenderit in voluptate velit esse cillum dolore eu fugiat nulla pariatur. Excepteur sint occaecat cupidatat non proident.",
        "image": "../assets/images/comece.jpg",
        "type" : "Arrumar" 
    },

    {
        "blogId": 19,
        "title" : "Featured Post",
        "largetitle" : "Design tips for designers that cover everything you need",
        "by" : "John Doe", 
        "date" : "May 23 2022",
        "desc" : "Duis aute irure dolor in reprehenderit in voluptate velit esse cillum dolore eu fugiat nulla pariatur. Excepteur sint occaecat cupidatat non proident.",
        "image": "../assets/images/aventura.jpg",
        "type" : "Aventura" 
    },

    {
        "blogId": 20,
        "title" : "Featured Post",
        "largetitle" : "Design tips for designers that cover everything you need",
        "by" : "John Doe", 
        "date" : "May 23 2022",
        "desc" : "Duis aute irure dolor in reprehenderit in voluptate velit esse cillum dolore eu fugiat nulla pariatur. Excepteur sint occaecat cupidatat non proident.",
        "image": "../assets/images/eletrico.jpg",
        "type" : "Comece" 
    },

    {
        "blogId": 21,
        "title" : "Featured Post",
        "largetitle" : "Design tips for designers that cover everything you need",
        "by" : "John Doe", 
        "date" : "May 23 2022",
        "desc" : "Duis aute irure dolor in reprehenderit in voluptate velit esse cillum dolore eu fugiat nulla pariatur. Excepteur sint occaecat cupidatat non proident.",
        "image": "../assets/images/programa.jpg",
        "type" : "Startup" 
    },

    {
        "blogId": 22,
        "title" : "Featured Post",
        "largetitle" : "Design tips for designers that cover everything you need",
        "by" : "John Doe", 
        "date" : "May 23 2023",
        "desc" : "Duis aute irure dolor in reprehenderit in voluptate velit esse cillum dolore eu fugiat nulla pariatur. Excepteur sint occaecat cupidatat non proident.",
        "image": "../assets/images/bicicleta.jpg",
        "type" : "Bom" 
    }
]